cancerstformer-0.1.0a0.dist-info/licenses/LICENSE
stFormer/classifier/Classifier.py
stFormer/classifier/__init__.py
stFormer/classifier/classifier_utils.py
stFormer/classifier/evaluation_utils.py
stFormer/classifier/train_classifier.py
stFormer/network_dynamics/__init__.py
stFormer/network_dynamics/gene_regulatory_network.py
stFormer/perturbation/__init__.py
stFormer/perturbation/embs.py
stFormer/perturbation/perturb_stats.py
stFormer/perturbation/perturb_utils.py
stFormer/perturbation/stFormer_perturb.py
stFormer/pretrain/__init__.py
stFormer/pretrain/deepspeed.py
stFormer/pretrain/hyperparameter_pretrainer.py
stFormer/pretrain/pretrainer.py
stFormer/pretrain/stFormer_pretrainer.py
stFormer/tokenization/SpatialTokenize.py
stFormer/tokenization/__init__.py
stFormer/tokenization/embedding_extractor.py
stFormer/tokenization/median_estimator.py
stFormer/tokenization/tokenization_spot_chunked.py
stFormer/tokenization/tokenize_spatial.py
cancerstformer-0.1.0a0.dist-info/METADATA
cancerstformer-0.1.0a0.dist-info/WHEEL
cancerstformer-0.1.0a0.dist-info/top_level.txt
cancerstformer-0.1.0a0.dist-info/RECORD
